pynet/__init__.py
pynet/tensor.py
pynet/data/__init__.py
pynet/data/abstract.py
pynet/data/in_memory.py
pynet/functional/__init__.py
pynet/functional/abstract.py
pynet/functional/add.py
pynet/functional/matmul.py
pynet/functional/max.py
pynet/functional/sigmoid.py
pynet/initializers/__init__.py
pynet/initializers/abstract.py
pynet/initializers/he_normal.py
pynet/loss/__init__.py
pynet/loss/abstract.py
pynet/loss/bce.py
pynet/loss/mse.py
pynet/nn/__init__.py
pynet/nn/abstract.py
pynet/nn/linear.py
pynet/nn/relu.py
pynet/nn/sequential.py
pynet/nn/sigmoid.py
pynet/optimizers/__init__.py
pynet/optimizers/abstract.py
pynet/optimizers/sgd.py
pynet/training/__init__.py
pynet/training/history.py
pynet/training/stats.py
pynet/training/callbacks/__init__.py
pynet/training/callbacks/abstract.py
pynet/training/callbacks/lr_schedule.py
pynet/training/callbacks/print.py
pynet/training/trainer/__init__.py
pynet/training/trainer/abstract.py
pynet/training/trainer/default.py
pynet_dl-0.0.10.dist-info/LICENSE
pynet_dl-0.0.10.dist-info/METADATA
pynet_dl-0.0.10.dist-info/WHEEL
pynet_dl-0.0.10.dist-info/top_level.txt
pynet_dl-0.0.10.dist-info/RECORD
