Metadata-Version: 2.1
Name: pynet-dl
Version: 0.0.10
Summary: Deep learning library
Home-page: https://github.com/r-papso/pynet
Author: Rastislav Papso
Author-email: rastislav.papso@gmail.com
License: UNKNOWN
Project-URL: Bug Tracker, https://github.com/r-papso/pynet/issues
Platform: UNKNOWN
Classifier: Programming Language :: Python :: 3
Classifier: License :: OSI Approved :: MIT License
Classifier: Operating System :: OS Independent
Requires-Python: >=3.9
License-File: LICENSE
Requires-Dist: numpy (>=1.21.2)
